{
  "account-type": "member",
  "environments": [
    {
      "name": "development",
      "access": [
        {
          "github_slug": "dts-legacy",
          "level": "sandbox"
        }
      ]
    },
    {
      "name": "preproduction",
      "access": [
        {
          "github_slug": "dts-legacy",
          "level": "developer"
        }
      ]
    },
    {
      "name": "production",
      "access": [
        {
          "github_slug": "dts-legacy",
          "level": "developer"
        }
      ]
    }
  ],
  "tags": {
    "application": "dacp",
    "business-unit": "HMCTS",
    "infrastructure-support": "DTS-ITServiceDesk@justice.gov.uk",
    "owner": "DTS-ITServiceDesk@justice.gov.uk"
  },
  "github-oidc-team-repositories": ["ministryofjustice/Dacp"],
  "go-live-date": "2023-10-04"
}
