{
  "cidr": {
    "subnet_sets": {
      "general": {
        "cidr": "10.26.16.0/21",
        "accounts": [
          "analytical-platform-compute-development",
          "analytical-platform-ingestion-development",
          "coat-development",
          "dummy-account-development",
          "example-development",
          "data-platform-development",
          "observability-platform-development",
          "operations-engineering-development",
          "panda-cyber-appsec-lab-development"
        ]
      }
    }
  },
  "options": {
    "bastion_linux": true,
    "additional_cidrs": [],
    "additional_endpoints": [],
    "additional_private_zones": [],
    "additional_vpcs": [],
    "dns_zone_extend": []
  }
}
